[{"買進年度":2017,"買進個股數":16,"平均持有月數":17.62,"總報酬率":164.74,"平均單次買進報酬率":10.3,"平均年報酬率":6.96,"勝率":62.5,"獲利次數":10,"虧損次數":6,"最大報酬率":95.2,"最小報酬率":-20},{"買進年度":2016,"買進個股數":22,"平均持有月數":17.86,"總報酬率":427.2,"平均單次買進報酬率":19.42,"平均年報酬率":13.08,"勝率":59.09,"獲利次數":13,"虧損次數":9,"最大報酬率":91.63,"最小報酬率":-20},{"買進年度":2015,"買進個股數":24,"平均持有月數":18,"總報酬率":-87.8,"平均單次買進報酬率":-3.66,"平均年報酬率":-2.4,"勝率":20.83,"獲利次數":5,"虧損次數":19,"最大報酬率":125.99,"最小報酬率":-20},{"買進年度":2014,"買進個股數":23,"平均持有月數":17.09,"總報酬率":216.78,"平均單次買進報酬率":9.43,"平均年報酬率":6.6,"勝率":13.04,"獲利次數":3,"虧損次數":20,"最大報酬率":443.43,"最小報酬率":-20},{"買進年度":2013,"買進個股數":26,"平均持有月數":16.92,"總報酬率":-166.48,"平均單次買進報酬率":-6.4,"平均年報酬率":-4.56,"勝率":30.77,"獲利次數":8,"虧損次數":18,"最大報酬率":45.52,"最小報酬率":-20},{"買進年度":2012,"買進個股數":26,"平均持有月數":17.85,"總報酬率":863.3,"平均單次買進報酬率":33.2,"平均年報酬率":22.32,"勝率":65.38,"獲利次數":17,"虧損次數":9,"最大報酬率":173.67,"最小報酬率":-20},{"買進年度":2011,"買進個股數":29,"平均持有月數":18,"總報酬率":803.68,"平均單次買進報酬率":27.71,"平均年報酬率":18.48,"勝率":58.62,"獲利次數":17,"虧損次數":12,"最大報酬率":494.59,"最小報酬率":-20},{"買進年度":2010,"買進個股數":15,"平均持有月數":17.13,"總報酬率":135.91,"平均單次買進報酬率":9.06,"平均年報酬率":6.36,"勝率":60,"獲利次數":9,"虧損次數":6,"最大報酬率":69.46,"最小報酬率":-20},{"買進年度":2009,"買進個股數":28,"平均持有月數":18,"總報酬率":2330.43,"平均單次買進報酬率":83.23,"平均年報酬率":55.44,"勝率":92.86,"獲利次數":26,"虧損次數":2,"最大報酬率":271.08,"最小報酬率":-19.16},{"買進年度":2008,"買進個股數":41,"平均持有月數":18,"總報酬率":173.05,"平均單次買進報酬率":4.22,"平均年報酬率":2.76,"勝率":34.15,"獲利次數":14,"虧損次數":27,"最大報酬率":89.92,"最小報酬率":-20},{"買進年度":2007,"買進個股數":40,"平均持有月數":18,"總報酬率":-119.17,"平均單次買進報酬率":-2.98,"平均年報酬率":-2.04,"勝率":17.5,"獲利次數":7,"虧損次數":33,"最大報酬率":147.16,"最小報酬率":-20},{"買進年度":2006,"買進個股數":30,"平均持有月數":17.77,"總報酬率":1765.9,"平均單次買進報酬率":58.86,"平均年報酬率":39.72,"勝率":80,"獲利次數":24,"虧損次數":6,"最大報酬率":438.2,"最小報酬率":-20},{"買進年度":2005,"買進個股數":28,"平均持有月數":18,"總報酬率":1575.56,"平均單次買進報酬率":56.27,"平均年報酬率":37.56,"勝率":75,"獲利次數":21,"虧損次數":7,"最大報酬率":252.2,"最小報酬率":-20},{"買進年度":2004,"買進個股數":28,"平均持有月數":18,"總報酬率":98.29,"平均單次買進報酬率":3.51,"平均年報酬率":2.28,"勝率":28.57,"獲利次數":8,"虧損次數":20,"最大報酬率":97.08,"最小報酬率":-20},{"買進年度":2003,"買進個股數":10,"平均持有月數":18,"總報酬率":-38.3,"平均單次買進報酬率":-3.83,"平均年報酬率":-2.52,"勝率":30,"獲利次數":3,"虧損次數":7,"最大報酬率":58.21,"最小報酬率":-20}]